simorc/__init__.py
simorc-0.0.0.dist-info/METADATA
simorc-0.0.0.dist-info/WHEEL
simorc-0.0.0.dist-info/RECORD
