Metadata-Version: 2.4
Name: simorc
Version: 0.0.0
Summary: A simulation orchestration tool.
Project-URL: Homepage, https://github.com/Jianxun/simorc
Project-URL: Bug Tracker, https://github.com/Jianxun/simorc/issues
Author-email: Jianxun Zhu <zhujianxun.bupt@gmail.com>
Classifier: License :: OSI Approved :: MIT License
Classifier: Operating System :: OS Independent
Classifier: Programming Language :: Python :: 3
Requires-Python: >=3.8
